cozmoclad/LICENSE.txt
cozmoclad/__init__.py
cozmoclad/clad/__init__.py
cozmoclad/clad/audio/__init__.py
cozmoclad/clad/audio/audioBusTypes.py
cozmoclad/clad/audio/audioCallbackMessage.py
cozmoclad/clad/audio/audioEventTypes.py
cozmoclad/clad/audio/audioGameObjectTypes.py
cozmoclad/clad/audio/audioMessage.py
cozmoclad/clad/audio/audioMessageTypes.py
cozmoclad/clad/audio/audioParameterTypes.py
cozmoclad/clad/audio/audioSoundbanks.py
cozmoclad/clad/audio/audioStateTypes.py
cozmoclad/clad/audio/audioSwitchTypes.py
cozmoclad/clad/audio/messageAudioClient.py
cozmoclad/clad/externalInterface/__init__.py
cozmoclad/clad/externalInterface/messageActions.py
cozmoclad/clad/externalInterface/messageEngineToGame.py
cozmoclad/clad/externalInterface/messageEngineToGame_hash.py
cozmoclad/clad/externalInterface/messageGameToEngine.py
cozmoclad/clad/externalInterface/messageGameToEngine_hash.py
cozmoclad/clad/externalInterface/messageShared.py
cozmoclad/clad/externalInterface/messageToBehaviorManager.py
cozmoclad/clad/physicsInterface/__init__.py
cozmoclad/clad/physicsInterface/messageSimPhysics.py
cozmoclad/clad/robotInterface/__init__.py
cozmoclad/clad/robotInterface/bleMessages.py
cozmoclad/clad/robotInterface/messageFromActiveObject.py
cozmoclad/clad/robotInterface/messageToActiveObject.py
cozmoclad/clad/types/__init__.py
cozmoclad/clad/types/actionResults.py
cozmoclad/clad/types/actionTypes.py
cozmoclad/clad/types/activeObjectAccel.py
cozmoclad/clad/types/activeObjectConstants.py
cozmoclad/clad/types/advertisementTypes.py
cozmoclad/clad/types/animationEvents.py
cozmoclad/clad/types/animationTrigger.py
cozmoclad/clad/types/birthCertificate.py
cozmoclad/clad/types/cladPoint.py
cozmoclad/clad/types/cladRect.py
cozmoclad/clad/types/controllerChannels.py
cozmoclad/clad/types/customObjectMarkers.py
cozmoclad/clad/types/debugConsoleTypes.py
cozmoclad/clad/types/deviceDataTypes.py
cozmoclad/clad/types/emotionTypes.py
cozmoclad/clad/types/engineErrorCodes.py
cozmoclad-3.3.0.dist-info/LICENSE-header-cs.txt
cozmoclad-3.3.0.dist-info/LICENSE-header-py.txt
cozmoclad-3.3.0.dist-info/LICENSE.txt
cozmoclad-3.3.0.dist-info/METADATA
cozmoclad-3.3.0.dist-info/WHEEL
cozmoclad-3.3.0.dist-info/top_level.txt
cozmoclad-3.3.0.dist-info/zip-safe
cozmoclad-3.3.0.dist-info/RECORD
