Metadata-Version: 2.1
Name: cozmoclad
Version: 3.3.0
Summary: Low-level protocol for the Anki Cozmo SDK.
Home-page: https://developer.anki.com/cozmo/
Author: Anki, Inc
Author-email: cozmosdk@anki.com
License: Apache License, Version 2.0
Platform: UNKNOWN
Classifier: Development Status :: 4 - Beta
Classifier: Intended Audience :: Developers
Classifier: Topic :: Software Development :: Libraries
Classifier: License :: OSI Approved :: Apache Software License
Classifier: Programming Language :: Python :: 3.5
